README.txt
setup.py
collective/__init__.py
collective.gacontext.egg-info/PKG-INFO
collective.gacontext.egg-info/SOURCES.txt
collective.gacontext.egg-info/dependency_links.txt
collective.gacontext.egg-info/entry_points.txt
collective.gacontext.egg-info/namespace_packages.txt
collective.gacontext.egg-info/not-zip-safe
collective.gacontext.egg-info/requires.txt
collective.gacontext.egg-info/top_level.txt
collective/gacontext/CHANGELOG
collective/gacontext/__init__.py
collective/gacontext/adapters.py
collective/gacontext/configure.zcml
collective/gacontext/interfaces.py
collective/gacontext/utilities.py
collective/gacontext/browser/__init__.py
collective/gacontext/browser/browser.py
collective/gacontext/browser/configure.zcml
collective/gacontext/browser/viewlets.py
collective/gacontext/profiles/default/actions.xml
collective/gacontext/profiles/default/metadata.xml
docs/HISTORY.txt
docs/INSTALL.txt
docs/LICENSE.GPL
docs/LICENSE.txt