Metadata-Version: 1.0
Name: collective.gacontext
Version: 0.2.1
Summary: Context dependend GoogleAnalytics
Home-page: https://svn.plone.org/svn/collective/collective.gacontext/trunk
Author: InQuant GmbH
Author-email: ramon.bartl@inquant.de
License: GPL
Platform: UNKNOWN
Classifier: Framework :: Plone
Classifier: Framework :: Zope2
Classifier: Framework :: Zope3
Classifier: Programming Language :: Python
Classifier: Topic :: Software Development :: Libraries :: Python Modules
